TMDA/Address.py
TMDA/Auth.py
TMDA/AutoResponse.py
TMDA/Cookie.py
TMDA/Defaults.py
TMDA/Deliver.py
TMDA/Errors.py
TMDA/FilterParser.py
TMDA/MTA.py
TMDA/MessageLogger.py
TMDA/Pending.py
TMDA/SMTP.py
TMDA/Util.py
TMDA/Version.py
TMDA/__init__.py
TMDA/Queue/MaildirQueue.py
TMDA/Queue/OriginalQueue.py
TMDA/Queue/Queue.py
TMDA/Queue/Util.py
TMDA/Queue/__init__.py
TMDAretro-1.1.13.20190604.0.data/data/share/tmda/doc/CODENAMES
TMDAretro-1.1.13.20190604.0.data/data/share/tmda/doc/COPYING
TMDAretro-1.1.13.20190604.0.data/data/share/tmda/doc/CRYPTO
TMDAretro-1.1.13.20190604.0.data/data/share/tmda/doc/ChangeLog
TMDAretro-1.1.13.20190604.0.data/data/share/tmda/doc/NEWS
TMDAretro-1.1.13.20190604.0.data/data/share/tmda/doc/README
TMDAretro-1.1.13.20190604.0.data/data/share/tmda/doc/README.md
TMDAretro-1.1.13.20190604.0.data/data/share/tmda/doc/THANKS
TMDAretro-1.1.13.20190604.0.data/data/share/tmda/doc/UPGRADE
TMDAretro-1.1.13.20190604.0.data/data/share/tmda/skeleton/dot-tmda/README
TMDAretro-1.1.13.20190604.0.data/data/share/tmda/skeleton/dot-tmda/config
TMDAretro-1.1.13.20190604.0.data/data/share/tmda/skeleton/dot-tmda/crypt_key
TMDAretro-1.1.13.20190604.0.data/data/share/tmda/skeleton/dot-tmda/filters/incoming
TMDAretro-1.1.13.20190604.0.data/data/share/tmda/skeleton/dot-tmda/filters/outgoing
TMDAretro-1.1.13.20190604.0.data/data/share/tmda/skeleton/dot-tmda/lists/blacklist
TMDAretro-1.1.13.20190604.0.data/data/share/tmda/skeleton/dot-tmda/lists/confirmed
TMDAretro-1.1.13.20190604.0.data/data/share/tmda/skeleton/dot-tmda/lists/whitelist
TMDAretro-1.1.13.20190604.0.data/data/share/tmda/templates/bounce_expired_dated.txt
TMDAretro-1.1.13.20190604.0.data/data/share/tmda/templates/bounce_fail_dated.txt
TMDAretro-1.1.13.20190604.0.data/data/share/tmda/templates/bounce_fail_keyword.txt
TMDAretro-1.1.13.20190604.0.data/data/share/tmda/templates/bounce_fail_sender.txt
TMDAretro-1.1.13.20190604.0.dist-info/DESCRIPTION.rst
TMDAretro-1.1.13.20190604.0.dist-info/METADATA
TMDAretro-1.1.13.20190604.0.dist-info/RECORD
TMDAretro-1.1.13.20190604.0.dist-info/WHEEL
TMDAretro-1.1.13.20190604.0.dist-info/metadata.json
TMDAretro-1.1.13.20190604.0.dist-info/top_level.txt
